pycounts_poc/__init__.py
pycounts_poc/data/__init__.py
pycounts_poc/data/flatland.txt
pycounts_poc/datasets.py
pycounts_poc/plotting.py
pycounts_poc/pycounts_poc.py
pycounts_poc-0.3.1.dist-info/LICENSE
pycounts_poc-0.3.1.dist-info/METADATA
pycounts_poc-0.3.1.dist-info/WHEEL
pycounts_poc-0.3.1.dist-info/RECORD
